{
    "has_execution_error": false,
    "execution_output": "SOLUTION:\n{\n  \"itinerary\": [\n    {\n      \"action\": \"meet\",\n      \"person\": \"Melissa\",\n      \"start_time\": \"10:29\",\n      \"end_time\": \"12:14\"\n    },\n    {\n      \"action\": \"meet\",\n      \"person\": \"James\",\n      \"start_time\": \"10:29\",\n      \"end_time\": \"11:59\"\n    },\n    {\n      \"action\": \"meet\",\n      \"person\": \"Betty\",\n      \"start_time\": \"10:32\",\n      \"end_time\": \"12:17\"\n    },\n    {\n      \"action\": \"meet\",\n      \"person\": \"Anthony\",\n      \"start_time\": \"11:45\",\n      \"end_time\": \"13:00\"\n    },\n    {\n      \"action\": \"meet\",\n      \"person\": \"Joshua\",\n      \"start_time\": \"12:15\",\n      \"end_time\": \"13:45\"\n    },\n    {\n      \"action\": \"meet\",\n      \"person\": \"Jeffrey\",\n      \"start_time\": \"12:15\",\n      \"end_time\": \"13:00\"\n    },\n    {\n      \"action\": \"meet\",\n      \"person\": \"Timothy\",\n      \"start_time\": \"12:30\",\n      \"end_time\": \"14:00\"\n    },\n    {\n      \"action\": \"meet\",\n      \"person\": \"Emily\",\n      \"start_time\": \"19:30\",\n      \"end_time\": \"21:30\"\n    }\n  ]\n}\n",
    "pred": {
        "itinerary": [
            {
                "action": "meet",
                "person": "Melissa",
                "start_time": "10:29",
                "end_time": "12:14"
            },
            {
                "action": "meet",
                "person": "James",
                "start_time": "10:29",
                "end_time": "11:59"
            },
            {
                "action": "meet",
                "person": "Betty",
                "start_time": "10:32",
                "end_time": "12:17"
            },
            {
                "action": "meet",
                "person": "Anthony",
                "start_time": "11:45",
                "end_time": "13:00"
            },
            {
                "action": "meet",
                "person": "Joshua",
                "start_time": "12:15",
                "end_time": "13:45"
            },
            {
                "action": "meet",
                "person": "Jeffrey",
                "start_time": "12:15",
                "end_time": "13:00"
            },
            {
                "action": "meet",
                "person": "Timothy",
                "start_time": "12:30",
                "end_time": "14:00"
            },
            {
                "action": "meet",
                "person": "Emily",
                "start_time": "19:30",
                "end_time": "21:30"
            }
        ]
    },
    "gold": {
        "itinerary": [
            {
                "action": "meet",
                "person": "Betty",
                "start_time": "09:13",
                "end_time": "10:58"
            },
            {
                "action": "meet",
                "person": "Melissa",
                "start_time": "11:13",
                "end_time": "12:58"
            },
            {
                "action": "meet",
                "person": "Joshua",
                "start_time": "13:03",
                "end_time": "14:33"
            },
            {
                "action": "meet",
                "person": "Jeffrey",
                "start_time": "14:50",
                "end_time": "15:35"
            },
            {
                "action": "meet",
                "person": "James",
                "start_time": "16:02",
                "end_time": "17:32"
            },
            {
                "action": "meet",
                "person": "Emily",
                "start_time": "19:30",
                "end_time": "21:30"
            }
        ]
    },
    "status": "Wrong plan",
    "violated_constraint": {
        "travel": {
            "from_person": "Melissa",
            "to_person": "James",
            "from_location": "Alamo Square",
            "to_location": "Bayview",
            "travel_time": 16
        }
    },
    "is_exact_match": false,
    "constraints_satisfied": false,
    "pass_number": 3
}