{
    "has_execution_error": false,
    "execution_output": "Meeting with Helen is not possible.\n{\n    \"itinerary\": [\n        {\n            \"action\": \"meet\",\n            \"location\": \"Pacific Heights\",\n            \"person\": \"Kevin\",\n            \"start_time\": \"09:30\",\n            \"end_time\": \"10:30\"\n        },\n        {\n            \"action\": \"meet\",\n            \"location\": \"Golden Gate Park\",\n            \"person\": \"Michelle\",\n            \"start_time\": \"20:00\",\n            \"end_time\": \"20:15\"\n        },\n        {\n            \"action\": \"meet\",\n            \"location\": \"Fisherman's Wharf\",\n            \"person\": \"Emily\",\n            \"start_time\": \"16:15\",\n            \"end_time\": \"19:00\"\n        },\n        {\n            \"action\": \"meet\",\n            \"location\": \"Marina District\",\n            \"person\": \"Mark\",\n            \"start_time\": \"18:15\",\n            \"end_time\": \"20:45\"\n        },\n        {\n            \"action\": \"meet\",\n            \"location\": \"Alamo Square\",\n            \"person\": \"Barbara\",\n            \"start_time\": \"17:00\",\n            \"end_time\": \"19:00\"\n        },\n        {\n            \"action\": \"meet\",\n            \"location\": \"Sunset District\",\n            \"person\": \"Laura\",\n            \"start_time\": \"19:00\",\n            \"end_time\": \"21:15\"\n        },\n        {\n            \"action\": \"meet\",\n            \"location\": \"Nob Hill\",\n            \"person\": \"Mary\",\n            \"start_time\": \"17:30\",\n            \"end_time\": \"19:00\"\n        }\n    ]\n}",
    "pred": {
        "itinerary": [
            {
                "action": "meet",
                "location": "Pacific Heights",
                "person": "Kevin",
                "start_time": "9:30",
                "end_time": "10:30"
            },
            {
                "action": "meet",
                "location": "Fisherman's Wharf",
                "person": "Emily",
                "start_time": "16:15",
                "end_time": "19:00"
            },
            {
                "action": "meet",
                "location": "Alamo Square",
                "person": "Barbara",
                "start_time": "17:00",
                "end_time": "19:00"
            },
            {
                "action": "meet",
                "location": "Nob Hill",
                "person": "Mary",
                "start_time": "17:30",
                "end_time": "19:00"
            },
            {
                "action": "meet",
                "location": "Marina District",
                "person": "Mark",
                "start_time": "18:15",
                "end_time": "20:45"
            },
            {
                "action": "meet",
                "location": "Sunset District",
                "person": "Laura",
                "start_time": "19:00",
                "end_time": "21:15"
            },
            {
                "action": "meet",
                "location": "Golden Gate Park",
                "person": "Michelle",
                "start_time": "20:00",
                "end_time": "20:15"
            }
        ]
    },
    "gold": {
        "itinerary": [
            {
                "action": "meet",
                "location": "North Beach",
                "person": "Helen",
                "start_time": "11:00",
                "end_time": "11:45"
            },
            {
                "action": "meet",
                "location": "Fisherman's Wharf",
                "person": "Emily",
                "start_time": "16:15",
                "end_time": "16:45"
            },
            {
                "action": "meet",
                "location": "Nob Hill",
                "person": "Mary",
                "start_time": "17:30",
                "end_time": "18:15"
            },
            {
                "action": "meet",
                "location": "Marina District",
                "person": "Mark",
                "start_time": "18:26",
                "end_time": "19:41"
            },
            {
                "action": "meet",
                "location": "Golden Gate Park",
                "person": "Michelle",
                "start_time": "20:00",
                "end_time": "20:15"
            }
        ]
    },
    "status": "Wrong plan",
    "violated_constraint": {
        "person": "Kevin",
        "time_of_day": {
            "from": "7:15AM",
            "to": "8:45AM"
        }
    },
    "is_exact_match": false,
    "constraints_satisfied": false,
    "pass_number": 5,
    "timing": {
        "api_call_time": 36.85867381095886,
        "execution_time": 0.02162027359008789,
        "constraint_eval_time": 0.00011229515075683594,
        "pred_extract_time": 1.7226617336273193,
        "gold_extract_time": 5.173683166503906e-05,
        "token_count": 0
    }
}