{
    "has_execution_error": false,
    "execution_output": "Feasible Schedule Found:\nStarting at Union Square at 9:00AM\n\nTravel from Union Square to The Castro: 19 mins\nMeet Robert at The Castro:\n  Start: 08:30\n  End: 09:00\n  Duration: 30 minutes\n\nTravel from The Castro to Chinatown: 20 mins\nMeet Rebecca at Chinatown:\n  Start: 09:45\n  End: 11:15\n  Duration: 90 minutes\n\nTravel from Chinatown to Golden Gate Park: 23 mins\nMeet Andrew at Golden Gate Park:\n  Start: 11:45\n  End: 13:00\n  Duration: 75 minutes\n\nTravel from Golden Gate Park to Pacific Heights: 16 mins\nMeet Sarah at Pacific Heights:\n  Start: 16:15\n  End: 16:30\n  Duration: 15 minutes\n\nTravel from Pacific Heights to Presidio: 11 mins\nMeet Nancy at Presidio:\n  Start: 17:30\n  End: 18:30\n  Duration: 60 minutes\n\nAll 5 friends successfully scheduled!\n",
    "pred": {
        "itinerary": [
            {
                "action": "meet",
                "person": "Robert",
                "start_time": "09:00",
                "end_time": "09:30"
            },
            {
                "action": "meet",
                "person": "Rebecca",
                "start_time": "09:45",
                "end_time": "11:15"
            },
            {
                "action": "meet",
                "person": "Andrew",
                "start_time": "11:45",
                "end_time": "13:00"
            },
            {
                "action": "meet",
                "person": "Sarah",
                "start_time": "16:15",
                "end_time": "16:30"
            },
            {
                "action": "meet",
                "person": "Nancy",
                "start_time": "17:30",
                "end_time": "18:30"
            }
        ]
    },
    "gold": {
        "itinerary": [
            {
                "action": "meet",
                "person": "Andrew",
                "start_time": "11:45",
                "end_time": "13:00"
            },
            {
                "action": "meet",
                "person": "Robert",
                "start_time": "13:13",
                "end_time": "13:43"
            },
            {
                "action": "meet",
                "person": "Sarah",
                "start_time": "16:15",
                "end_time": "16:30"
            },
            {
                "action": "meet",
                "person": "Nancy",
                "start_time": "17:30",
                "end_time": "18:30"
            },
            {
                "action": "meet",
                "person": "Rebecca",
                "start_time": "18:51",
                "end_time": "20:21"
            }
        ]
    },
    "status": "Wrong plan",
    "violated_constraint": {
        "travel_start": {
            "to_person": "Robert",
            "to_location": "The Castro",
            "travel_time": 19
        }
    },
    "is_exact_match": false,
    "constraints_satisfied": false,
    "pass_number": 5
}